odoo/addons/l10n_ro_stock_account_tracing/README.rst
odoo/addons/l10n_ro_stock_account_tracing/__init__.py
odoo/addons/l10n_ro_stock_account_tracing/__manifest__.py
odoo/addons/l10n_ro_stock_account_tracing/i18n/l10n_ro_stock_account_tracing.pot
odoo/addons/l10n_ro_stock_account_tracing/models/__init__.py
odoo/addons/l10n_ro_stock_account_tracing/models/account_move_line.py
odoo/addons/l10n_ro_stock_account_tracing/models/picking.py
odoo/addons/l10n_ro_stock_account_tracing/models/stock_valuation_layer.py
odoo/addons/l10n_ro_stock_account_tracing/readme/CONTRIBUTORS.rst
odoo/addons/l10n_ro_stock_account_tracing/readme/DESCRIPTION.rst
odoo/addons/l10n_ro_stock_account_tracing/static/description/icon.png
odoo/addons/l10n_ro_stock_account_tracing/static/description/icon.svg
odoo/addons/l10n_ro_stock_account_tracing/static/description/index.html
odoo/addons/l10n_ro_stock_account_tracing/views/stock_valuation_layer.xml
odoo14_addon_l10n_ro_stock_account_tracing-14.0.0.1.0.dist-info/METADATA
odoo14_addon_l10n_ro_stock_account_tracing-14.0.0.1.0.dist-info/WHEEL
odoo14_addon_l10n_ro_stock_account_tracing-14.0.0.1.0.dist-info/top_level.txt
odoo14_addon_l10n_ro_stock_account_tracing-14.0.0.1.0.dist-info/RECORD
